[
    {
        "value": 1.0,
        "label": 1.0,
        "children": [
            {
                "value": "祛鲜红斑痣",
                "label": "祛鲜红斑痣"
            },
            {
                "value": "祛瘢痕疙瘩",
                "label": "祛瘢痕疙瘩"
            },
            {
                "value": "祛蝴蝶斑",
                "label": "祛蝴蝶斑"
            },
            {
                "value": "射频紧肤",
                "label": "射频紧肤"
            },
            {
                "value": "去疣",
                "label": "去疣"
            },
            {
                "value": "注射溶解酶",
                "label": "注射溶解酶"
            },
            {
                "value": "注射肉毒素",
                "label": "注射肉毒素"
            },
            {
                "value": "祛毛周角化",
                "label": "祛毛周角化"
            },
            {
                "value": "牙贴面",
                "label": "牙贴面"
            },
            {
                "value": "纹绣",
                "label": "纹绣"
            },
            {
                "value": "全身吸脂",
                "label": "全身吸脂"
            },
            {
                "value": "金属矫正",
                "label": "金属矫正"
            },
            {
                "value": "全身脱毛",
                "label": "全身脱毛"
            },
            {
                "value": "祛雀斑样痣",
                "label": "祛雀斑样痣"
            }
        ]
    },
    {
        "value": 2.0,
        "label": 2.0,
        "children": [
            {
                "value": "皮肤保养",
                "label": "皮肤保养"
            },
            {
                "value": "皮肤检测",
                "label": "皮肤检测"
            },
            {
                "value": "祛深层斑",
                "label": "祛深层斑"
            },
            {
                "value": "祛褐青色痣",
                "label": "祛褐青色痣"
            },
            {
                "value": "嫩肤",
                "label": "嫩肤"
            },
            {
                "value": "光子嫩肤",
                "label": "光子嫩肤"
            },
            {
                "value": "根管治疗",
                "label": "根管治疗"
            },
            {
                "value": "吸脂修复",
                "label": "吸脂修复"
            },
            {
                "value": "美容冠",
                "label": "美容冠"
            },
            {
                "value": "打轮廓针",
                "label": "打轮廓针"
            },
            {
                "value": "牙冠修复",
                "label": "牙冠修复"
            },
            {
                "value": "半隐形矫正",
                "label": "半隐形矫正"
            },
            {
                "value": "除氟斑牙",
                "label": "除氟斑牙"
            },
            {
                "value": "冷光美白",
                "label": "冷光美白"
            }
        ]
    },
    {
        "value": 3.0,
        "label": 3.0,
        "children": [
            {
                "value": "下巴假体取出",
                "label": "下巴假体取出"
            },
            {
                "value": "玻尿酸丰太阳穴",
                "label": "玻尿酸丰太阳穴"
            },
            {
                "value": "梨涡成形",
                "label": "梨涡成形"
            },
            {
                "value": "疤痕修复",
                "label": "疤痕修复"
            },
            {
                "value": "皓齿美白",
                "label": "皓齿美白"
            },
            {
                "value": "祛脂肪粒",
                "label": "祛脂肪粒"
            },
            {
                "value": "多点双眼皮",
                "label": "多点双眼皮"
            },
            {
                "value": "玻尿酸溶解鼻部",
                "label": "玻尿酸溶解鼻部"
            },
            {
                "value": "男士脱毛",
                "label": "男士脱毛"
            },
            {
                "value": "自体脂肪丰太阳穴",
                "label": "自体脂肪丰太阳穴"
            },
            {
                "value": "私密保养",
                "label": "私密保养"
            },
            {
                "value": "洗纹绣",
                "label": "洗纹绣"
            },
            {
                "value": "疤痕未拆线",
                "label": "疤痕未拆线"
            },
            {
                "value": "自体脂肪丰唇",
                "label": "自体脂肪丰唇"
            }
        ]
    },
    {
        "value": 4.0,
        "label": 4.0,
        "children": [
            {
                "value": "美瞳线修复",
                "label": "美瞳线修复"
            },
            {
                "value": "祛萎缩性疤痕",
                "label": "祛萎缩性疤痕"
            },
            {
                "value": "祛褐青斑",
                "label": "祛褐青斑"
            },
            {
                "value": "果酸焕肤",
                "label": "果酸焕肤"
            },
            {
                "value": "颈部松弛修复",
                "label": "颈部松弛修复"
            },
            {
                "value": "玻尿酸注射耳垂",
                "label": "玻尿酸注射耳垂"
            },
            {
                "value": "窝沟封闭",
                "label": "窝沟封闭"
            },
            {
                "value": "祛伊藤痣",
                "label": "祛伊藤痣"
            },
            {
                "value": "祛贝壳痣",
                "label": "祛贝壳痣"
            },
            {
                "value": "埋线减肥",
                "label": "埋线减肥"
            },
            {
                "value": "大腿吸脂修复",
                "label": "大腿吸脂修复"
            },
            {
                "value": "埋线提拉",
                "label": "埋线提拉"
            },
            {
                "value": "耳部修复",
                "label": "耳部修复"
            },
            {
                "value": "假体取出",
                "label": "假体取出"
            }
        ]
    },
    {
        "value": 5.0,
        "label": 5.0,
        "children": [
            {
                "value": "祛颊纹",
                "label": "祛颊纹"
            },
            {
                "value": "面部无创类",
                "label": "面部无创类"
            },
            {
                "value": "颧骨部位脱毛",
                "label": "颧骨部位脱毛"
            },
            {
                "value": "自体脂肪丰耳垂",
                "label": "自体脂肪丰耳垂"
            },
            {
                "value": "其他标签",
                "label": "其他标签"
            },
            {
                "value": "无主题",
                "label": "无主题"
            }
        ]
    }
]